preprocessing/__init__.py
preprocessing/etl_utils.py
preprocessing/read_mf4.py
preprocessing/ros_etl_utils.py
rosbag2_mf4_preprocessing_tools-0.4.35.dist-info/METADATA
rosbag2_mf4_preprocessing_tools-0.4.35.dist-info/WHEEL
rosbag2_mf4_preprocessing_tools-0.4.35.dist-info/top_level.txt
rosbag2_mf4_preprocessing_tools-0.4.35.dist-info/RECORD
