Metadata-Version: 2.4
Name: rosbag2_mf4_preprocessing_tools
Version: 0.4.35
Summary: Tools for preprocessing MF4 and Rosbag files in an Airflow DAG.
Author-email: Bora <bbpilav@gmail.com>
Project-URL: Homepage, https://github.com/yourusername/mf4_processor_package
Project-URL: Bug Tracker, https://github.com/yourusername/mf4_processor_package/issues
Classifier: Programming Language :: Python :: 3
Classifier: License :: OSI Approved :: MIT License
Classifier: Operating System :: OS Independent
Requires-Python: >=3.8
Requires-Dist: numpy
Requires-Dist: tables
Requires-Dist: asammdf
Requires-Dist: pandas
Requires-Dist: pyyaml
